fixinventoryappbundler/__init__.py
fixinventoryappbundler/__main__.py
fixinventoryappbundler/bundler.py
fixinventoryappbundler/runner.py
fixinventoryappbundler-0.5.0.dist-info/LICENSE
fixinventoryappbundler-0.5.0.dist-info/METADATA
fixinventoryappbundler-0.5.0.dist-info/WHEEL
fixinventoryappbundler-0.5.0.dist-info/entry_points.txt
fixinventoryappbundler-0.5.0.dist-info/top_level.txt
fixinventoryappbundler-0.5.0.dist-info/RECORD
