Metadata-Version: 2.1
Name: fixinventoryappbundler
Version: 0.5.0
Summary: Bundles Fix Inventory Apps into a single artifact.
Home-page: https://github.com/someengineering/fixinventoryappbundler
License: Apache 2.0
Keywords: cloud security
Classifier: Development Status :: 4 - Beta
Classifier: Intended Audience :: System Administrators
Classifier: Intended Audience :: Information Technology
Classifier: License :: OSI Approved :: Apache Software License
Classifier: Programming Language :: Python :: 3.9
Classifier: Operating System :: POSIX :: Linux
Classifier: Operating System :: Unix
Classifier: Environment :: Console
Classifier: Natural Language :: English
Classifier: Topic :: Security
Classifier: Topic :: Utilities
License-File: LICENSE
Requires-Dist: PyYAML ==6.0
Requires-Dist: Jinja2 ==3.1.3
Requires-Dist: fixinventorylib >=3.5.2
